{
    "burglary": [
        "unemployment_rate",
        "avg_income",
        "building_density",
        "land_area_density",
        "road_density",
        "log_population",
        "distance_km",
        "year",
        "week_of_year",
        "week_sin",
        "week_cos",
        "avg_victim_age_lag1",
        "avg_victim_age_lag2",
        "avg_victim_age_roll4",
        "female_victim_ratio_lag1",
        "female_victim_ratio_lag2",
        "female_victim_ratio_roll4",
        "urban_ratio_lag1",
        "urban_ratio_lag2",
        "urban_ratio_roll4",
        "holiday_ratio_lag1",
        "holiday_ratio_lag2",
        "holiday_ratio_roll4",
        "rainy_ratio_lag1",
        "rainy_ratio_lag2",
        "rainy_ratio_roll4",
        "total_crimes_lag1",
        "total_crimes_lag2",
        "total_crimes_lag4",
        "total_crimes_roll4",
        "total_crimes_roll8",
        "total_crimes_trend_4v8",
        "burglary_count_lag1",
        "burglary_count_lag2",
        "burglary_count_lag4",
        "burglary_count_roll4",
        "burglary_count_roll8",
        "burglary_count_trend_4v8"
    ],
    "theft": [
        "unemployment_rate",
        "avg_income",
        "building_density",
        "land_area_density",
        "road_density",
        "log_population",
        "distance_km",
        "year",
        "week_of_year",
        "week_sin",
        "week_cos",
        "avg_victim_age_lag1",
        "avg_victim_age_lag2",
        "avg_victim_age_roll4",
        "female_victim_ratio_lag1",
        "female_victim_ratio_lag2",
        "female_victim_ratio_roll4",
        "urban_ratio_lag1",
        "urban_ratio_lag2",
        "urban_ratio_roll4",
        "holiday_ratio_lag1",
        "holiday_ratio_lag2",
        "holiday_ratio_roll4",
        "rainy_ratio_lag1",
        "rainy_ratio_lag2",
        "rainy_ratio_roll4",
        "total_crimes_lag1",
        "total_crimes_lag2",
        "total_crimes_lag4",
        "total_crimes_roll4",
        "total_crimes_roll8",
        "total_crimes_trend_4v8",
        "theft_count_lag1",
        "theft_count_lag2",
        "theft_count_lag4",
        "theft_count_roll4",
        "theft_count_roll8",
        "theft_count_trend_4v8"
    ],
    "vehicle": [
        "unemployment_rate",
        "avg_income",
        "building_density",
        "land_area_density",
        "road_density",
        "log_population",
        "distance_km",
        "year",
        "week_of_year",
        "week_sin",
        "week_cos",
        "avg_victim_age_lag1",
        "avg_victim_age_lag2",
        "avg_victim_age_roll4",
        "female_victim_ratio_lag1",
        "female_victim_ratio_lag2",
        "female_victim_ratio_roll4",
        "urban_ratio_lag1",
        "urban_ratio_lag2",
        "urban_ratio_roll4",
        "holiday_ratio_lag1",
        "holiday_ratio_lag2",
        "holiday_ratio_roll4",
        "rainy_ratio_lag1",
        "rainy_ratio_lag2",
        "rainy_ratio_roll4",
        "total_crimes_lag1",
        "total_crimes_lag2",
        "total_crimes_lag4",
        "total_crimes_roll4",
        "total_crimes_roll8",
        "total_crimes_trend_4v8",
        "vehicle_count_lag1",
        "vehicle_count_lag2",
        "vehicle_count_lag4",
        "vehicle_count_roll4",
        "vehicle_count_roll8",
        "vehicle_count_trend_4v8"
    ],
    "robbery": [
        "unemployment_rate",
        "avg_income",
        "building_density",
        "land_area_density",
        "road_density",
        "log_population",
        "distance_km",
        "year",
        "week_of_year",
        "week_sin",
        "week_cos",
        "avg_victim_age_lag1",
        "avg_victim_age_lag2",
        "avg_victim_age_roll4",
        "female_victim_ratio_lag1",
        "female_victim_ratio_lag2",
        "female_victim_ratio_roll4",
        "urban_ratio_lag1",
        "urban_ratio_lag2",
        "urban_ratio_roll4",
        "holiday_ratio_lag1",
        "holiday_ratio_lag2",
        "holiday_ratio_roll4",
        "rainy_ratio_lag1",
        "rainy_ratio_lag2",
        "rainy_ratio_roll4",
        "total_crimes_lag1",
        "total_crimes_lag2",
        "total_crimes_lag4",
        "total_crimes_roll4",
        "total_crimes_roll8",
        "total_crimes_trend_4v8",
        "robbery_count_lag1",
        "robbery_count_lag2",
        "robbery_count_lag4",
        "robbery_count_roll4",
        "robbery_count_roll8",
        "robbery_count_trend_4v8"
    ],
    "drugs": [
        "unemployment_rate",
        "avg_income",
        "building_density",
        "land_area_density",
        "road_density",
        "log_population",
        "distance_km",
        "year",
        "week_of_year",
        "week_sin",
        "week_cos",
        "avg_victim_age_lag1",
        "avg_victim_age_lag2",
        "avg_victim_age_roll4",
        "female_victim_ratio_lag1",
        "female_victim_ratio_lag2",
        "female_victim_ratio_roll4",
        "urban_ratio_lag1",
        "urban_ratio_lag2",
        "urban_ratio_roll4",
        "holiday_ratio_lag1",
        "holiday_ratio_lag2",
        "holiday_ratio_roll4",
        "rainy_ratio_lag1",
        "rainy_ratio_lag2",
        "rainy_ratio_roll4",
        "total_crimes_lag1",
        "total_crimes_lag2",
        "total_crimes_lag4",
        "total_crimes_roll4",
        "total_crimes_roll8",
        "total_crimes_trend_4v8",
        "drugs_count_lag1",
        "drugs_count_lag2",
        "drugs_count_lag4",
        "drugs_count_roll4",
        "drugs_count_roll8",
        "drugs_count_trend_4v8"
    ],
    "stabbing": [
        "unemployment_rate",
        "avg_income",
        "building_density",
        "land_area_density",
        "road_density",
        "log_population",
        "distance_km",
        "year",
        "week_of_year",
        "week_sin",
        "week_cos",
        "avg_victim_age_lag1",
        "avg_victim_age_lag2",
        "avg_victim_age_roll4",
        "female_victim_ratio_lag1",
        "female_victim_ratio_lag2",
        "female_victim_ratio_roll4",
        "urban_ratio_lag1",
        "urban_ratio_lag2",
        "urban_ratio_roll4",
        "holiday_ratio_lag1",
        "holiday_ratio_lag2",
        "holiday_ratio_roll4",
        "rainy_ratio_lag1",
        "rainy_ratio_lag2",
        "rainy_ratio_roll4",
        "total_crimes_lag1",
        "total_crimes_lag2",
        "total_crimes_lag4",
        "total_crimes_roll4",
        "total_crimes_roll8",
        "total_crimes_trend_4v8",
        "stabbing_count_lag1",
        "stabbing_count_lag2",
        "stabbing_count_lag4",
        "stabbing_count_roll4",
        "stabbing_count_roll8",
        "stabbing_count_trend_4v8"
    ]
}